leadtools/__init__.py
leadtools/__pkginfo__.py
leadtools/_info.py
leadtools/_loader.py
leadtools/_platform.py
leadtools/bin/CDLL/x64/LTDocWrtAltox.dll
leadtools/bin/CDLL/x64/LTDocWrtDocx.dll
leadtools/bin/CDLL/x64/LTDocWrtDocxx.dll
leadtools/bin/CDLL/x64/LTDocWrtEmfx.dll
leadtools/bin/CDLL/x64/LTDocWrtHtmx.dll
leadtools/bin/CDLL/x64/LTDocWrtPdfx.dll
leadtools/bin/CDLL/x64/LTDocWrtRtfx.dll
leadtools/bin/CDLL/x64/LTDocWrtTtfx.dll
leadtools/bin/CDLL/x64/LTDocWrtTxtx.dll
leadtools/bin/CDLL/x64/LTDocWrtXlsx.dll
leadtools/bin/CDLL/x64/LTDocWrtXpsx.dll
leadtools/bin/CDLL/x64/Lf3jsx.dll
leadtools/bin/CDLL/x64/LfAfpx.dll
leadtools/bin/CDLL/x64/LfDoxx.dll
leadtools/bin/CDLL/x64/LfPpxx.dll
leadtools/bin/CDLL/x64/LfX9Fx.dll
leadtools/bin/CDLL/x64/LfXlxx.dll
leadtools/bin/CDLL/x64/LfXmpx.dll
leadtools/bin/CDLL/x64/Lfabix.dll
leadtools/bin/CDLL/x64/Lfacsx.dll
leadtools/bin/CDLL/x64/Lfanix.dll
leadtools/bin/CDLL/x64/Lfanzx.dll
leadtools/bin/CDLL/x64/Lfbmpx.dll
leadtools/bin/CDLL/x64/Lfcalx.dll
leadtools/bin/CDLL/x64/Lfcgmx.dll
leadtools/bin/CDLL/x64/Lfcinx.dll
leadtools/bin/CDLL/x64/Lfclpx.dll
leadtools/bin/CDLL/x64/Lfcmpx.dll
leadtools/bin/CDLL/x64/Lfcmwx.dll
leadtools/bin/CDLL/x64/Lfcmxx.dll
leadtools/bin/CDLL/x64/Lfcutx.dll
leadtools/bin/CDLL/x64/Lfdcfx.dll
leadtools/bin/CDLL/x64/Lfdgnx.dll
leadtools/bin/CDLL/x64/Lfdocx.dll
leadtools/bin/CDLL/x64/Lfdrwx.dll
leadtools/bin/CDLL/x64/Lfdwfx.dll
leadtools/bin/CDLL/x64/Lfdwgx.dll
leadtools/bin/CDLL/x64/Lfdxfx.dll
leadtools/bin/CDLL/x64/Lfe00x.dll
leadtools/bin/CDLL/x64/Lfepsx.dll
leadtools/bin/CDLL/x64/Lffaxx.dll
leadtools/bin/CDLL/x64/Lffitx.dll
leadtools/bin/CDLL/x64/Lfflcx.dll
leadtools/bin/CDLL/x64/Lffpxx.dll
leadtools/bin/CDLL/x64/Lfgbrx.dll
leadtools/bin/CDLL/x64/Lfgifx.dll
leadtools/bin/CDLL/x64/Lfhdpx.dll
leadtools/bin/CDLL/x64/Lfheifx.dll
leadtools/bin/CDLL/x64/Lfhtmx.dll
leadtools/bin/CDLL/x64/Lficax.dll
leadtools/bin/CDLL/x64/Lfiffx.dll
leadtools/bin/CDLL/x64/Lfimgx.dll
leadtools/bin/CDLL/x64/Lfingx.dll
leadtools-23.0.0.5.dist-info/licenses/LICENSE
leadtools-23.0.0.5.dist-info/METADATA
leadtools-23.0.0.5.dist-info/WHEEL
leadtools-23.0.0.5.dist-info/top_level.txt
leadtools-23.0.0.5.dist-info/RECORD
