Metadata-Version: 2.4
Name: leadtools
Version: 23.0.0.5
Summary: Powered by patented artificial intelligence and machine learning algorithms, LEADTOOLS is a collection of comprehensive toolkits to integrate recognition, document, medical, imaging, and multimedia technologies into desktop, server, tablet, web and mobile solutions.
Author-email: "LEAD Technologies, Inc." <support@leadtools.com>
License: 
Project-URL: Homepage, https://www.leadtools.com
Project-URL: Documentation, https://www.leadtools.com/support/webhelp
Project-URL: Chat, https://www.leadtools.com/support/chat
Keywords: Intelligent Character Recognition,ICR,DOC,DOCX,XLS,XLSX,PPT,PPTX,TXT,ID,IDCard,receipt,convert,conversion,Office,Microsoft,audio,video,scan,recognition,lead,leadtools,lead-tools,imaging,multimedia,annotation,image,markup,image-markup,mark-up,document,viewer,OCR,MICR,OMR,PDF,PDF/A,XML,XPS,SVG,Optical Character Recognition,Barcode,UPC,EAN,Code 128,QR,Data Matrix,PDF417,Codes,UCC/EAN,UCC-128,EAN-128,EAN-14,GTIN-14,GS1,DataBar,RSS-14,4-State,POSTNET,USPS4CB,Codabar,extract,text,bookmarks,a
Classifier: Programming Language :: Python :: 3
Classifier: License :: Other/Proprietary License
Classifier: Operating System :: Microsoft :: Windows
Classifier: Development Status :: 5 - Production/Stable
Classifier: Intended Audience :: Developers
Classifier: Programming Language :: C#
Classifier: Programming Language :: Python
Classifier: Topic :: Software Development :: Build Tools
Requires-Python: >=3.7
License-File: LICENSE
Requires-Dist: pythonnet
Requires-Dist: leadtools_common_runtime
Dynamic: license-file
